jep_cmake/__init__.py
jep_cmake/analysis.py
jep_cmake/dispatch.py
jep_cmake/main.py
jep_cmake/model.py
jep_cmake/project.py
jep_cmake/built-ins/2.8.12-cmake.txt
jep_cmake/built-ins/2.8.12-ctest.txt
jep_cmake/built-ins/2.8.12-deprecated.txt
jep_cmake/built-ins/3.4-cmake.txt
jep_cmake/built-ins/3.4-ctest.txt
jep_cmake/built-ins/3.4-deprecated.txt
jep_cmake/parser/__init__.py
jep_cmake/parser/cmakeLexer.py
jep_cmake/parser/cmakeListener.py
jep_cmake/parser/cmakeParser.py
jep_cmake-0.0.3.dist-info/DESCRIPTION.rst
jep_cmake-0.0.3.dist-info/METADATA
jep_cmake-0.0.3.dist-info/RECORD
jep_cmake-0.0.3.dist-info/WHEEL
jep_cmake-0.0.3.dist-info/entry_points.txt
jep_cmake-0.0.3.dist-info/metadata.json
jep_cmake-0.0.3.dist-info/top_level.txt
