Metadata-Version: 2.0
Name: jep-cmake
Version: 0.0.3
Summary: CMake backend for JEP-enabled editors.
Home-page: https://github.com/jep-project/jep-cmake
Author: Mike Pagel
Author-email: mike@mpagel.de
License: UNKNOWN
Keywords: jep cmake language editor
Platform: UNKNOWN
Classifier: Development Status :: 3 - Alpha
Classifier: Intended Audience :: End Users/Desktop
Classifier: Topic :: Software Development
Classifier: License :: OSI Approved :: MIT License
Classifier: Programming Language :: Python :: 3.3
Classifier: Programming Language :: Python :: 3.4
Classifier: Programming Language :: Python :: 3.5
Requires-Dist: antlr4-python3-runtime
Requires-Dist: chardet
Requires-Dist: jep-python
